dataidea_science/__init__.py
dataidea_science/_modidx.py
dataidea_science/core.py
dataidea_science/datasets.py
dataidea_science/plots.py
dataidea_science/preprocessing.py
dataidea_science-0.0.1.dist-info/LICENSE
dataidea_science-0.0.1.dist-info/METADATA
dataidea_science-0.0.1.dist-info/WHEEL
dataidea_science-0.0.1.dist-info/entry_points.txt
dataidea_science-0.0.1.dist-info/top_level.txt
dataidea_science-0.0.1.dist-info/RECORD
